ghprofile/__init__.py
ghprofile/core.py
ghprofile-0.2.0.dist-info/licenses/LICENSE
ghprofile-0.2.0.dist-info/METADATA
ghprofile-0.2.0.dist-info/WHEEL
ghprofile-0.2.0.dist-info/top_level.txt
ghprofile-0.2.0.dist-info/RECORD
