Metadata-Version: 2.4
Name: ghprofile
Version: 0.2.0
Summary: A lightweight library to fetch and summarize GitHub user data
Author-email: Ujjwal Baunthiyal <baunthiyalujjwal52@gmail.com>
License: MIT License
Project-URL: Homepage, https://github.com/ujjwaluzu/ghprofile
Project-URL: Source, https://github.com/ujjwaluzu/ghprofile
Requires-Python: >=3.7
License-File: LICENSE
Requires-Dist: requests
Requires-Dist: beautifulsoup4
Dynamic: license-file
